LICENSE.txt
MANIFEST.in
README.md
setup.cfg
setup.py
django_zip_code_api.egg-info/PKG-INFO
django_zip_code_api.egg-info/SOURCES.txt
django_zip_code_api.egg-info/dependency_links.txt
django_zip_code_api.egg-info/requires.txt
django_zip_code_api.egg-info/top_level.txt
project/__init__.py
project/settings.py
project/urls.py
project/wsgi.py
zip_code_api/__init__.py
zip_code_api/conf.py
zip_code_api/models.py
zip_code_api/pagination.py
zip_code_api/serializers.py
zip_code_api/urls.py
zip_code_api/views.py
zip_code_api/management/__init__.py
zip_code_api/management/commands/__init__.py
zip_code_api/management/commands/load_zip_code_from_csv.py
zip_code_api/migrations/0001_initial.py
zip_code_api/migrations/__init__.py