Metadata-Version: 2.1
Name: django-zip-code-api
Version: 1.4.2
Summary: Zip Code API is an API for zip codes (postal codes) and addresses requesting. Optimized for polish addresses, however might work as universal tool.
Home-page: https://integree.eu/en/solutions/zip-code-api/
Author: Integree Bussines Solutions
License: UNKNOWN
Platform: UNKNOWN
Classifier: Development Status :: 5 - Production/Stable
Classifier: Intended Audience :: Developers
Classifier: Operating System :: OS Independent
Classifier: Environment :: Web Environment
Classifier: Programming Language :: Python :: 3.6
Classifier: Programming Language :: Python :: 2.7
Classifier: Framework :: Django :: 2.0
Classifier: Framework :: Django :: 1.11
Classifier: License :: OSI Approved :: MIT License
